AUTHORS.rst
CONTRIBUTING.rst
HISTORY.rst
LICENSE
MANIFEST.in
README.rst
setup.cfg
setup.py
docs/Makefile
docs/authors.rst
docs/conf.py
docs/contributing.rst
docs/history.rst
docs/index.rst
docs/installation.rst
docs/make.bat
docs/readme.rst
docs/usage.rst
requirements/requirements.txt
tests/__init__.py
tests/conftest.py
tests/test_files.py
tests/test_strings.py
tests/test_utils.py
texools/__init__.py
texools/files.py
texools/strings.py
texools/utils.py
texools.egg-info/PKG-INFO
texools.egg-info/SOURCES.txt
texools.egg-info/dependency_links.txt
texools.egg-info/not-zip-safe
texools.egg-info/requires.txt
texools.egg-info/top_level.txt