Metadata-Version: 1.1
Name: texools
Version: 0.3.0
Summary: Package containing tools for working with text and text files.
Home-page: https://github.com/cw-andrews/texools
Author: CW Andrews
Author-email: cwandrews.oh@gmail.com
License: MIT license
Keywords: texools
Platform: UNKNOWN
Classifier: Development Status :: 2 - Pre-Alpha
Classifier: Intended Audience :: Developers
Classifier: License :: OSI Approved :: MIT License
Classifier: Natural Language :: English
Classifier: Programming Language :: Python :: 3.4
Classifier: Programming Language :: Python :: 3.5
Classifier: Programming Language :: Python :: 3.6
